LICENSE
MANIFEST.in
README.rst
setup.py
django_treeadmin_fork_alt_storage.egg-info/PKG-INFO
django_treeadmin_fork_alt_storage.egg-info/SOURCES.txt
django_treeadmin_fork_alt_storage.egg-info/dependency_links.txt
django_treeadmin_fork_alt_storage.egg-info/not-zip-safe
django_treeadmin_fork_alt_storage.egg-info/requires.txt
django_treeadmin_fork_alt_storage.egg-info/top_level.txt
docs/index.rst
treeadmin/__init__.py
treeadmin/admin.py
treeadmin/static/treeadmin/css/treeadmin.css
treeadmin/static/treeadmin/img/arrow-move.png
treeadmin/static/treeadmin/img/disclosure-down.png
treeadmin/static/treeadmin/img/disclosure-right.png
treeadmin/static/treeadmin/img/drag_order_circle.png
treeadmin/static/treeadmin/js/ie_compat.js
treeadmin/static/treeadmin/js/jquery-1.7.min.js
treeadmin/static/treeadmin/js/jquery-ui-1.8.16.custom.min.js
treeadmin/static/treeadmin/js/jquery.cookie.js
treeadmin/static/treeadmin/js/toolbox.js
treeadmin/static/treeadmin/js/treeadmin.js
treeadmin/templates/admin/treeadmin/tree_editor.html