Metadata-Version: 1.0
Name: django-treeadmin-fork-alt-storage
Version: 0.5
Summary: Tree UI for mptt-managed models, extracted from FeinCMS. This is a fork with support for alternative storage engines
Home-page: https://www.github.com/KristianOellegaard/django-treeadmin
Author: Matthias Kestenholz  et al.
Author-email: mk@spinlock.ch
License: UNKNOWN
Platform: UNKNOWN
Classifier: Development Status :: 3 - Alpha
Classifier: Framework :: Django
Classifier: Intended Audience :: Developers
Classifier: License :: OSI Approved :: BSD License
Classifier: Operating System :: OS Independent
Classifier: Programming Language :: Python :: 2.5
Classifier: Programming Language :: Python :: 2.6
Classifier: Programming Language :: Python :: 2.7
Classifier: Topic :: Internet :: WWW/HTTP :: Dynamic Content
